{
  "collected_at": "2026-04-06T00:00:00",
  "items": [
    {
      "title": "マクロスΔ 10周年記念プロジェクト始動",
      "summary": "2026年4月3日でTV放送開始10周年を迎えたマクロスΔの記念プロジェクトが正式始動。実田千聖による描き下ろし10周年記念イラストとPVが公開され、今後の展開が注目される。",
      "url": "https://dengekionline.com/article/202604/70830",
      "source": "電撃オンライン",
      "date": "2026-04-03",
      "category": "news"
    },
    {
      "title": "マクロスF × トップガン マーヴェリック コラボ発表",
      "summary": "マクロスFと映画トップガン・マーヴェリックの初コラボが実現。「DX超合金 VF-25 メサイアバルキリー トップガン マーヴェリックVer.」が2026年9月発売予定（26,400円）で4月3日より予約開始。バトロイド・ガウォーク・ファイターの3形態に変形可能。",
      "url": "https://macross.jp/contents/1061318",
      "source": "MACROSS OFFICIAL SITE",
      "date": "2026-03-31",
      "category": "news"
    },
    {
      "title": "マクロスシリーズ新作発表スペシャル放送",
      "summary": "サンライズ制作によるマクロスシリーズ新作の続報を含む「新作発表スペシャル」が3月2日19時にフジテレビ系列で放送された。アニメ全4シリーズの一挙放送も同時に実施された。",
      "url": "https://www.famitsu.com/article/202502/34366",
      "source": "ファミ通",
      "date": "2026-03-02",
      "category": "news"
    },
    {
      "title": "ユニオンアリーナ「マクロス」シリーズVol.2（EX14BT）発売決定",
      "summary": "マクロスダイナマイト7・ゼロ・劇場版マクロスF2作品・マクロスΔを収録したTCG第2弾が2026年6月19日発売予定（BOX 6,160円）。Δキャラデザのまじろによるワルキューレ5名の新規描き下ろしイラストを使用したSR等、計77種＋AP7種。",
      "url": "https://macross.jp/contents/1037870",
      "source": "MACROSS OFFICIAL SITE",
      "date": "2026-06-19",
      "category": "goods"
    },
    {
      "title": "DX超合金 VF-31A カイロス マクロスΔ 10th Anniv. 商品化",
      "summary": "マクロスΔ10周年を記念したBANDAI SPIRITS製「DX超合金 VF-31A カイロス マクロスΔ10th Anniv.」の商品化が発表。10周年の節目にあわせた記念モデル。",
      "url": "https://macross.jp/contents/1001932",
      "source": "MACROSS OFFICIAL SITE",
      "date": "2026-04-03",
      "category": "goods"
    },
    {
      "title": "MACROSS POP UP STORE ～あなたとラッピング・パーティー♪～ 開催決定",
      "summary": "マクロスFとマクロスΔのポップアップストア「MACROSS POP UP STORE ～あなたとラッピング・パーティー♪～」の開催が公式サイトで発表された。詳細な開催期間・場所は公式サイトを参照。",
      "url": "https://macross.jp/contents/1061855",
      "source": "MACROSS OFFICIAL SITE",
      "date": null,
      "category": "events"
    },
    {
      "title": "マクロスF ポップアップステージ at CG STAR LIVE（池袋）",
      "summary": "池袋のバンダイナムコ Cross Store 東京にて、シェリル・ノームとランカ・リーが登場する「マクロスF ポップアップステージ」が2026年6月24日（土）〜8月27日（日）の期間開催予定。観覧チケット1枚につきオリジナルノベルティのプレゼントあり。",
      "url": "https://bandainamco-am.co.jp/am/vg/cgslive/program/popupstage.php",
      "source": "CG STAR LIVE",
      "date": "2026-06-24",
      "category": "events"
    },
    {
      "title": "映画『迷宮のしおり』2026年1月1日全国ロードショー",
      "summary": "河森正治初のオリジナル劇場長編アニメーション「迷宮のしおり」が2026年元日に全国公開。スマートフォンをテーマにした異世界脱出青春劇で、サンジゲン制作。主題歌は新しい学校のリーダーズのSUZUKAが担当。東京国際映画祭にも出品された。",
      "url": "https://gaga.ne.jp/meikyu-shiori/",
      "source": "映画『迷宮のしおり』公式サイト",
      "date": "2026-01-01",
      "person": "kawamori"
    },
    {
      "title": "『迷宮のしおり』公開記念舞台挨拶（TOHOシネマズ日比谷）",
      "summary": "2026年1月5日にTOHOシネマズ日比谷で公開記念舞台挨拶が開催。河森正治監督とSUZUKA・伊東蒼・寺西拓人らキャストが和服姿で登壇し、鏡割りで新春の公開を祝った。",
      "url": "https://v-storage.jp/anime/etc-anime/265222/",
      "source": "V-STORAGE",
      "date": "2026-01-05",
      "person": "kawamori"
    },
    {
      "title": "河森正治 創作展フィナーレイベント（万博記念公園 EXPO'70パビリオン）",
      "summary": "2026年1月17〜18日に大阪・万博記念公園EXPO'70パビリオンで創作展のフィナーレイベントを開催。17日は私物サイン会を1日4回実施（11:00/12:30/14:00/15:30）、18日はトークショーを1日4回実施した。",
      "url": "https://prtimes.jp/main/html/rd/p/000000036.000122231.html",
      "source": "PRTimes / Vector Vision",
      "date": "2026-01-17",
      "person": "kawamori"
    },
    {
      "title": "マクロスF × トップガン コラボについて河森監督がSNSでコメント",
      "summary": "マクロスシリーズの生みの親である河森正治監督が、VF-25メサイアバルキリーとトップガン・マーヴェリックのコラボ実現について、SNS上で喜びのコメントを発表。ハリウッド映画との初コラボとして大きな反響を呼んでいる。",
      "url": "https://macross.jp/contents/1061318",
      "source": "MACROSS OFFICIAL SITE / X(@kawamoriexpo)",
      "date": "2026-03-31",
      "person": "kawamori"
    },
    {
      "title": "May'n 20th Anniversary Live Tour 2026「THE BEST of May'n」国内3公演",
      "summary": "デビュー20周年記念の全国ツアーが2026年3月に実施。3月8日Zepp名古屋、3月15日Zepp難波、3月21日Zepp羽田の計3公演で開催（開場15:30・開演16:15）。各会場でツアーグッズの先行販売も実施。",
      "url": "https://www.sound-c.co.jp/sp/mayn26/",
      "source": "May'n 20周年スペシャルサイト",
      "date": "2026-03-08",
      "person": "mayn"
    },
    {
      "title": "May'n 20th Anniversary Live Tour 2026 台北公演",
      "summary": "20周年ライブツアーの海外公演として、2026年5月10日（日）に台湾・Zepp New Taipeiで台北公演を開催。OPEN 16:30 / START 17:30。",
      "url": "https://mayn.jp/news/live/mayn-20th-anniversary-live-tour-2026%E3%80%8Cthe-best-of-mayn%E3%80%8D%E5%8F%B0%E5%8C%97%E5%85%AC%E6%BC%94%E3%81%AB%E3%81%A4%E3%81%84%E3%81%A6%E3%81%AE%E3%81%94%E6%A1%88%E5%86%85/",
      "source": "May'n Official Site",
      "date": "2026-05-10",
      "person": "mayn"
    },
    {
      "title": "May'n ファンクラブ限定打ち上げパーティー（沖縄）",
      "summary": "20周年ツアーの締めくくりとして、2026年5月31日に沖縄でFC会員限定の打ち上げパーティーを開催予定。「ライ部」として会員とともに20周年を祝う特別なクロージングイベント。",
      "url": "https://mayn.jp/news/live/",
      "source": "May'n Official Site",
      "date": "2026-05-31",
      "person": "mayn"
    },
    {
      "title": "中島愛 電気ビル みらいホール（福岡）イベント",
      "summary": "2026年2月28日に福岡・電気ビル みらいホールで中島愛のイベントが開催。開場16:15・開演17:00。",
      "url": "https://qun.jp/event/59085",
      "source": "qun.jp",
      "date": "2026-02-28",
      "person": "nakajima"
    },
    {
      "title": "Nakajima Megumi Billboard Live 2026 in Yokohama",
      "summary": "中島愛がバンド編成で初夏のビルボードライブ横浜に登場。2026年6月6日（土）に2回公演（1st 16:00〜・2nd 19:00〜）。中村タイチ（Gt/バンマス）・田辺貴広（Dr）・森田晃平（Ba）・持山翔子（Pf）による5名編成。FC先行チケット：3月30日〜4月5日、一般発売：4月24日から。",
      "url": "https://www.billboard-live.com/yokohama/show?event_id=ev-21357",
      "source": "Billboard Live YOKOHAMA",
      "date": "2026-06-06",
      "person": "nakajima"
    }
  ]
}
